MANIFEST.in
setup.cfg
setup.py
versioneer.py
explorers/__init__.py
explorers/_version.py
explorers/channels.py
explorers/conduits.py
explorers/explorer.py
explorers/meshgrid.py
explorers/tools.py
explorers.egg-info/PKG-INFO
explorers.egg-info/SOURCES.txt
explorers.egg-info/dependency_links.txt
explorers.egg-info/pbr.json
explorers.egg-info/requires.txt
explorers.egg-info/top_level.txt
explorers/algorithms/__init__.py
explorers/algorithms/adapt.py
explorers/algorithms/diversities.py
explorers/algorithms/m_disturb.py
explorers/algorithms/m_mesh.py
explorers/algorithms/m_rand.py
explorers/algorithms/m_restrict.py
explorers/algorithms/meta.py
explorers/algorithms/s_frontier.py
explorers/algorithms/s_mesh.py
explorers/algorithms/s_rand.py
explorers/algorithms/s_restrict.py
explorers/algorithms/s_set.py
explorers/algorithms/s_unreach.py
explorers/algorithms/im/__init__.py
explorers/algorithms/im/im_grid.py
explorers/algorithms/im/im_mesh.py
explorers/algorithms/im/im_model.py
explorers/algorithms/reuse/__init__.py
explorers/algorithms/reuse/ark_reuse.py
explorers/algorithms/reuse/s_goalreuse.py
explorers/algorithms/reuse/s_manual_reuse.py
explorers/algorithms/reuse/s_multireuse.py
explorers/algorithms/reuse/s_reuse.py
explorers/algorithms/reuse/s_reusegen.py
explorers/algorithms/reuse/s_subreuse.py
test/test_goalreuse.py
test/test_im_mesh.py
test/test_m_rand.py
test/test_meshgrid.py
test/test_meta.py
test/test_multireuse.py
test/test_reuse_gen.py
test/test_s_mesh.py
test/test_s_rand.py
test/test_s_reuse.py
test/test_subreuse.py
test/test_tools.py
test/testenvs.py