Metadata-Version: 1.1
Name: explorers
Version: 1.2.0
Summary: Framework for autonomous exploration algorithms in sensorimotor spaces
Home-page: github.com/humm/explorers.git
Author: Fabien Benureau
Author-email: fabien.benureau@gmail.com
License: Open Science License (see fabien.benureau.com/openscience.html
Download-URL: https://github.com/humm/explorers/tarball/1.2.0
Keywords: exploration learning algorithm sensorimotor robots robotics
Platform: UNKNOWN
Classifier: Development Status :: 4 - Beta
Classifier: Programming Language :: Python :: 2.7
Classifier: Intended Audience :: Science/Research
